mcp_agent_client-0.0.1.dev1.dist-info/licenses/LICENSE
mcp_client/__init__.py
mcp_agent_client-0.0.1.dev1.dist-info/METADATA
mcp_agent_client-0.0.1.dev1.dist-info/WHEEL
mcp_agent_client-0.0.1.dev1.dist-info/top_level.txt
mcp_agent_client-0.0.1.dev1.dist-info/RECORD
