Metadata-Version: 2.4
Name: mcp-agent-client
Version: 0.0.1.dev1
Summary: Placeholder for the official Python SDK for the Intelligent Agents Platform (MCP). Coming soon!
Author-email: Federico Monfasani <fmonfasani@gmail.com>
License-Expression: MIT
Project-URL: Homepage, https://github.com/fmonfgasani/intelligent-agents-platform
Project-URL: Bug Tracker, https://github.com/fmonfasani/intelligent-agents-platform/issues
Classifier: Development Status :: 1 - Planning
Classifier: Programming Language :: Python :: 3
Classifier: Operating System :: OS Independent
Classifier: Intended Audience :: Developers
Classifier: Topic :: Software Development :: Libraries :: Python Modules
Requires-Python: >=3.8
License-File: LICENSE
Dynamic: license-file
